LICENSE.txt
README.rst
cleanup
ilan_dev.py
setup.py
tarinfo
ilan_dev.egg-info/PKG-INFO
ilan_dev.egg-info/SOURCES.txt
ilan_dev.egg-info/dependency_links.txt
ilan_dev.egg-info/top_level.txt